ctadl_ghidra_fact_generator_plugin/VERSION
ctadl_ghidra_fact_generator_plugin/__init__.py
ctadl_ghidra_fact_generator_plugin-0.0.2.dist-info/LICENSE.txt
ctadl_ghidra_fact_generator_plugin-0.0.2.dist-info/METADATA
ctadl_ghidra_fact_generator_plugin-0.0.2.dist-info/WHEEL
ctadl_ghidra_fact_generator_plugin-0.0.2.dist-info/top_level.txt
ctadl_ghidra_fact_generator_plugin-0.0.2.dist-info/RECORD
